{"uid":"567a99299657badd57349a81","page_index":0,"title":"GalNet Weekly Expansion List","date":"02 JAN 3302","url":"https://community.elitedangerous.com/galnet/uid/567a99299657badd57349a81","content":"Each week, GalNet presents a list of 10 of the 1,708 minor factions currently expanding into new systems.\nThiana United Group\nRegir Purple Legal PLC\nRevolutionary HR 6649 Republic Party\nAlliance of Cileni\nLP 694-16 Crimson Legal Ind\nGreen Party of Dulos\nGuangngel Freedom Party\nPrahlang PLC\nUnited Barillian Labour\nRevolutionary Betseoltana Future\nExpansion occurs when a minor faction reaches a sufficient influence rating and there is a populated system within striking distance. The act of expansion is a costly one, and the wealth and development rating suffers during the period of expansion.Data is correct at time of publishing.","extraction_date":"2021-03-22T02:35:11Z","deprecated":false}