{"uid":"575984f29657ba6e04b8baf9","pageIndex":2,"title":"Galactic News: Order Restored to Mehet","date":"09 JUN 3302","url":"https://community.elitedangerous.com/galnet/uid/575984f29657ba6e04b8baf9","content":"Mehet Ltd has announced that its campaign to clear the Mehet system of agitators has been a success. Hundreds of pilots responded to the appeal, taking to their ships to eliminate the criminals operating in the system.\nFollowing the success of the operation, Mehet Ltd released a brief statement to the media:\n\"Thanks to the brave Commanders of the Pilots Federation, Mehet is now free from the depredations of criminals and agitators. On behalf of the people of Mehet, we would like to express our gratitude.\"\nRewards for those who contributed to the initiative are now available for collection at Schwann Dock.","extractionDate":"2021-03-22T01:58:17Z","deprecated":false}