{"uid":"568e41dc9657bab01fb1b422","page_index":2,"title":"GalNet Focus on Democracy","date":"07 JAN 3302","url":"https://community.elitedangerous.com/galnet/uid/568e41dc9657bab01fb1b422","content":"This weekly roundup highlights some of the minor factions pursuing the dream of democratic freedom by holding elections.\nHere are 10 of the 3,271 minor factions holding elections:\nWenda Alliance Union\nYen K'an Protectorate\nMurung Services\nConservatives of Praavapri\nMCC 378 Vision Incorporated\nSublime Order of van Maanen's Star\nLeague of 36 Ursae Majoris\nLHS 1885 League\nLhou Xuang Prison Colony\nPartnership of Nareri\nElections occur when two minor factions of a similar political structure resolve a conflict over ownership and influence within a system. \nData is correct at time of publishing.","extraction_date":"2021-03-22T02:38:53Z","deprecated":false}