{"uid":"57cfe24e9657ba5f5e6ec88e","page_index":3,"title":"Galactic News: Weekly Health Report","date":"07 SEP 3302","url":"https://community.elitedangerous.com/galnet/uid/57cfe24e9657ba5f5e6ec88e","content":"This report presents the latest data on health issues among the galaxy's minor factions.\nHere are the latest factions to experience famine:\nLFT 1349 Mafia\nBPM 40823 Republic Party\n36 Ursae Majoris Gold Posse\nJustice Party of Orule\nCorngaranga Nationals\nConfederacy of 47 Ursae Majoris\nJet Major Co\nIktock Jet Family\nBoresti Blue United Corporation\t\nNjuwai Transport Co\nWhen a faction is affected by famine the standard of living in the system it controls temporarily decreases. Combat activity has no effect on influence while a famine is active. Completing food-trade missions can bring a famine to an end.\nHere are the latest factions to experience an outbreak:\nLHS 4003 Blue Organisation\nIndependent Kambila Confederacy\nTraditional Ackwada Order\nLFT 444 Crimson Energy Systems\nKokowar Solutions\nAdachit Solutions\nLeague of Rudrato\nSigma Hydri Gold Family\nHIP 14997 People's Party\nLTT 1935 Gold Galactic Network\nWhen a faction is affected by an outbreak the standard of living in the system it controls temporarily decreases. Combat activity has no effect on influence while an outbreak is active. Completing medicine-supply missions can bring an outbreak to an end.","extraction_date":"2021-03-22T02:19:19Z","deprecated":false}