{"uid":"592d532c557ca475dd5b93e6","pageIndex":0,"title":"Galactic News: Weekly Security Report","date":"31 MAY 3303","url":"https://community.elitedangerous.com/galnet/uid/592d532c557ca475dd5b93e6","content":"This report presents the latest data on the security status of the galaxy’s minor factions.\nHere are the latest factions to experience a lockdown:\nKokary Holdings\t\nZugen Incorporated\nRevolutionary HIP 6161 Unionists\nRevolutionary Zeus Values Party\nOpala Power Commodities\nHecate Creative Industries\nCrimson Major Incorporated\nAnurinjung Corp.\nPirates of Tiliala\nQuince Galactic Corporation\nWhen a faction experiences a lockdown, the security rating of the system it controls temporarily increases and the system’s wealth temporarily decreases. Bounty hunting activity can shorten the lockdown period.\nHere are the latest factions to experience civil unrest:\nApoyota Domain\nNew Zeta Tucanae Free\nConservatives of HIP 41984\nBhotho Rats\nRoss 490 Mafia\ni Bootis Democrats\nNationalists of Aulin\nAulin Focus\nEravapa Empire Group\nHIP 85360 Dynasty\nCivil unrest is the result of illegal activity. When a faction is affected by civil unrest, the standard of living in the system it controls temporarily decreases, as does the system’s wealth. Combat missions and activities can bring civil unrest to an end.","extractionDate":"2021-03-22T01:51:37Z","deprecated":false}