{"uid":"598aded662b0b24ab427e964","page_index":2,"title":"Galactic News: Weekly Health Report","date":"10 AUG 3303","url":"https://community.elitedangerous.com/galnet/uid/598aded662b0b24ab427e964","content":"This report presents the latest data on health issues among the galaxy’s minor factions.\nHere are the latest factions to experience famine:\nLeft Party of HIP 43845\nHIP 105577 One\nGCRV 4654 State Interstellar\nHIP 19773 Shared\nOlolos Drug Empire\nMarquis du HIP 110867\nIndependent HIP 108971 Values Party\nPi Pavonis Transport Corp.\nChukchair Prison Colony\nHIP 22500 Blue Partnership\nWhen a faction is affected by famine the standard of living in the system it controls temporarily decreases. Combat activity has no effect on influence while a famine is active. Completing food-trade missions can bring a famine to an end.\nHere are the latest factions to experience an outbreak:\nOfficial Darkates Freedom Party\t\nLiberty Party of Zeessze\nKvenland Services\nHIP 10570 Constitution Party\nAllied FK5 2550 Autocracy\nJamatia Central Corp.\nHatmehit Purple Crew\nHIP 32350 Industries\nHIP 15545 Public Network\nChukchair Fortune Group\nWhen a faction is affected by an outbreak the standard of living in the system it controls temporarily decreases. Combat activity has no effect on influence while an outbreak is active. Completing medicine-supply missions can bring an outbreak to an end."}