{"uid":"58cab4aa15ac1ccf3e97d90c","pageIndex":0,"title":"Galactic News: Construction Appeal Concludes","date":"16 MAR 3303","url":"https://community.elitedangerous.com/galnet/uid/58cab4aa15ac1ccf3e97d90c","content":"A spokesperson for the Military Militia has extended its gratitude to those who supported its recent appeal for construction materials. In a statement, the spokesperson said:\n\"Thanks to the galactic community, we are now in a position to start work on the Soldiers' Respite installation.\"\nPilots who contributed to the initiative can now collect their rewards from Pellegrino Hub in the XI-2 Lupi system.","extractionDate":"2021-03-22T01:56:20Z","deprecated":false}