{"uid":"59158d029c6c01201e66d567","page_index":0,"title":"Galactic News: Weekly Expansion Report","date":"14 MAY 3303","url":"https://community.elitedangerous.com/galnet/uid/59158d029c6c01201e66d567","content":"This report presents the latest data on expansion and withdrawal among the galaxy's minor factions.\nHere are the latest factions to have expanded into new systems:\nPartnership of Nitikaba\nAtung Mussa Purple Comms Ind\nYimanbin Nationalists\nOsuntes Interstellar\nCakutsi Movement\nKoing Dynasty\nDemocrats of HIP 57080\nUnion of Aiaba Partnership\nAwa One\nAlliance of Gunwini\nExpansions occur when a minor faction reaches a sufficient level of influence and there is a populated system within striking distance. Expansion is costly, so when a faction expands, the wealth and development level of the system it controls are temporarily reduced.\nHere are the latest factions in withdrawal:\nHIP 13269 Silver Drug Empire\nSui Xenates Indie Union\nMovement for Pienate Labour\nHIP 17984 Gold Brotherhood \nKikua Empire Party\nCoalition of Djagana\nUnified Tagarilocan\nKumbia Ltd\nWakam Central Commodities\nOrisala Co-operative\nFactions are considered to be in withdrawal if their level of influence within a system drops below a certain level. If the faction's influence remains low for a total of five days, the faction must leave the system entirely. If the faction manages to increase its level of influence, it remains in the system."}