{"uid":"59955d25095f26061751d3a8","page_index":3,"title":"Galactic News: Weekly Democracy Report","date":"18 AUG 3303","url":"https://community.elitedangerous.com/galnet/uid/59955d25095f26061751d3a8","content":"This report presents the latest data on democratic activity among the galaxy’s minor factions.\nHere are the latest factions to hold elections:\nBodb Den Advanced Network\nAymifa Resistance\nHIP 96289 Blue Major Inc\nZhu Veddi State Limited\nParhul Silver Electronics Hldgs\nAutocracy of Phi Gruis\nAmbivas Power Partners\nBD+07 4267 Gold General PLC\nLHS 3384 Progressive Party\nNuenets Corp. \nElections occur when two minor factions with a similar political structure resolve a conflict over ownership and influence within a system."}