{"uid":"5aaa66a740365a43355ebb50","pageIndex":1,"title":"Coalition of Othime Campaign Concludes","date":"16 MAR 3304","url":"https://community.elitedangerous.com/galnet/uid/5aaa66a740365a43355ebb50","content":"The Coalition of Othime has announced that its campaign to build a new asteroid base has received the wholehearted support of the galactic community. Hundreds of pilots supported the appeal by delivering commodities to Levi Montalcini Dock and by eliminating agitators in Othime, thereby ensuring the safety of traders.\nAuthorities in Othime have extended their gratitude to those who participated in the operation.\nPilots who contributed to the initiative can now collect their rewards from Levi-Montalcini Dock in the Othime system.","extractionDate":"2021-03-22T02:28:41Z","deprecated":false}