{"uid":"5a5787708a640c638d6d781d","pageIndex":0,"title":"One Year On","date":"12 JAN 3304","url":"https://community.elitedangerous.com/galnet/uid/5a5787708a640c638d6d781d","content":"It has now been a year since the Thargoids returned to human-occupied space, and in that time they have become increasingly aggressive, their hostility culminating in starport attacks in the Pleiades Nebula.\nNow that the Thargoids’ intentions have been made clear, the question many are asking is “what can we do?”\nOutspoken political commentator Daxton Sung offered the following analysis:\n“The situation continues to escalate and our leaders continue to offer the same tired platitudes – militaristic bombast from Hudson, noncommittal banalities from Lavigny-Duval and earnest sympathising from Mahon. It’s clear that they have no idea how to counter the Thargoid threat, beyond pumping more money into Aegis’s weapons programme.”","extractionDate":"2021-03-22T01:55:29Z","deprecated":false}