{"uid":"5baa485d52217347647b95a9","page_index":0,"title":"Starport Status Update","date":"25 SEP 3304","url":"https://community.elitedangerous.com/galnet/uid/5baa485d52217347647b95a9","content":"This report presents the latest data on starports experiencing technical issues as a result of Thargoid Sensor related interference.\nThe following starports are currently closed:\nBester Terminal, Jen Nik\nBlack Station, Lausang\nBurton Vision, Dimocorna\nCauchy Dock, Decht\nKlink Dock, Inino\nMouchez Platform, Deacon's Star\nPook Dock, HIP 35873\nRennie Hub, Kupol Bumba\nSemeonis Hub, Nuwach\nSinclair Colony, San Qin Gu\nSmith Landing, Amber\nSomerset Station, I Carinae\nWingqvist Terminal, NLTT 57216\nMeanwhile, the following starports are on the brink of closure:\nChomsky Terminal, San Tu\nCowper Dock, Anima\nMargulies Dock, Cornengu\nMars High, Sol\nPRE Research Base, HIP 17225\nRamsay City, Anagori\nSo-yeon Hub, Coma\nStrekalov Gateway, Ross 733\nWarren Prison Mine, Ross 128"}